kit/.DS_Store
kit/__init__.py
kit/__main__.py
kit/cmdline.py
kit/decorator/__init__.py
kit/decorator/cache.py
kit/decorator/deprecated.py
kit/decorator/lock.py
kit/decorator/type_assert.py
kit/dict/__init__.py
kit/dict/addict.py
kit/dict/operdict.py
kit/list/__init__.py
kit/list/operlist.py
kit/rpc/__init__.py
kit/rpc/app.py
kit/rpc/broker/__init__.py
kit/rpc/broker/base.py
kit/rpc/broker/cron.py
kit/rpc/broker/memory.py
kit/rpc/broker/rmq.py
kit/rpc/broker/web.py
kit/rpc/config/__init__.py
kit/rpc/config/nacos.py
kit/rpc/config/redis.py
kit/rpc/events.py
kit/rpc/job.py
kit/rpc/message.py
kit/rpc/middleware/__init__.py
kit/rpc/middleware/delay.py
kit/rpc/middleware/lock.py
kit/rpc/middleware/middleware.py
kit/rpc/middleware/transfer.py
kit/rpc/middleware/unique.py
kit/rpc/state.py
kit/rpc/store.py
kit/rpc/worker.py
kit/rpc2/__init__.py
kit/rpc2/app.py
kit/rpc2/broker/__init__.py
kit/rpc2/broker/base.py
kit/rpc2/broker/cron.py
kit/rpc2/broker/memory.py
kit/rpc2/broker/rmq.py
kit/rpc2/broker/web.py
kit/rpc2/config/__init__.py
kit/rpc2/config/nacos.py
kit/rpc2/config/redis.py
kit/rpc2/events.py
kit/rpc2/job.py
kit/rpc2/message-.py
kit/rpc2/message.py
kit/rpc2/middleware/__init__.py
kit/rpc2/middleware/delay.py
kit/rpc2/middleware/lock.py
kit/rpc2/middleware/middleware.py
kit/rpc2/middleware/transfer.py
kit/rpc2/middleware/unique.py
kit/rpc2/state.py
kit/rpc2/store.py
kit/rpc2/worker.py
kit/store/__init__.py
kit/store/rabbitmq.py
kit/store/redis_.py
kit/string_.py
kit/tool/__init__.py
kit/tool/clean_html.py
kit/tool/cookies_2_dict.py
kit/tool/current_platform.py
kit/tool/date_time.py
kit/tool/import_object.py
kit/tool/logger.py
kit/tool/random_useragent.py
kit/tool/registry.py
kit/tool/timer.py
kit_py-0.6.0.dist-info/METADATA
kit_py-0.6.0.dist-info/WHEEL
kit_py-0.6.0.dist-info/entry_points.txt
kit_py-0.6.0.dist-info/RECORD
