Metadata-Version: 2.1
Name: kit-py
Version: 0.6.0
Summary: 个人代码工具包
Home-page: https://github.com/mic1on/kit
Author: miclon
Author-email: jcnd@163.com
Requires-Python: >=3.8,<4.0
Classifier: Programming Language :: Python :: 3
Classifier: Programming Language :: Python :: 3.8
Classifier: Programming Language :: Python :: 3.9
Classifier: Programming Language :: Python :: 3.10
Classifier: Programming Language :: Python :: 3.11
Provides-Extra: all
Provides-Extra: dev
Provides-Extra: test
Requires-Dist: amqpstorm[rabbitmq] (>=2.10.5,<3.0.0)
Requires-Dist: croniter (>=1.3.8,<2.0.0)
Requires-Dist: fastapi (>=0.85.1,<0.86.0)
Requires-Dist: loguru (>=0.6.0,<0.7.0)
Requires-Dist: nacos-sdk-python (==0.1.8)
Requires-Dist: redis[redis] (>=4.3.4,<5.0.0)
Requires-Dist: uvicorn (>=0.19.0,<0.20.0)
